LICENSE
MANIFEST.in
README.rst
setup.cfg
setup.py
django_email/__init__.py
django_email/abstract_models.py
django_email/admin.py
django_email/apps.py
django_email/constants.py
django_email/exceptions.py
django_email/models.py
django_email/services.py
django_email/tasks.py
django_email/urls.py
django_email/views.py
django_email/migrations/0001_initial.py
django_email/migrations/0002_auto_20200528_1257.py
django_email/migrations/0003_emaillog_from_name.py
django_email/migrations/0004_auto_20200715_1943.py
django_email/migrations/0005_auto_20200716_1446.py
django_email/migrations/0006_auto_20200716_1518.py
django_email/migrations/__init__.py
django_email/providers/__init__.py
django_email/providers/abstract.py
django_email/providers/mailjet.py
django_email/tests/__init__.py
django_email/tests/factories.py
django_email/tests/test_mailjet.py
django_email/tests/test_models.py
django_email/tests/test_services.py
django_email/tests/test_urls.py
django_email/tests/test_views.py
django_email_service.egg-info/PKG-INFO
django_email_service.egg-info/SOURCES.txt
django_email_service.egg-info/dependency_links.txt
django_email_service.egg-info/requires.txt
django_email_service.egg-info/top_level.txt